dnlp/__init__.py
dnlp-0.0.0.dist-info/LICENSE
dnlp-0.0.0.dist-info/METADATA
dnlp-0.0.0.dist-info/WHEEL
dnlp-0.0.0.dist-info/top_level.txt
dnlp-0.0.0.dist-info/RECORD
